vb_bot/__init__.py
vb_bot/bot.py
vb_bot/configs/__init__.py
vb_bot/configs/bot_settings.py
vb_bot/configs/telegram_api.py
vb_bot/models/__init__.py
vb_bot/models/api_queue.py
vb_bot/models/connector.py
vb_bot/models/queue_callback.py
vb_bot/models/user.py
vb_bot/modules/__init__.py
vb_bot/modules/setup_logger.py
vb_bot-1.0.3.dist-info/LICENSE
vb_bot-1.0.3.dist-info/METADATA
vb_bot-1.0.3.dist-info/WHEEL
vb_bot-1.0.3.dist-info/top_level.txt
vb_bot-1.0.3.dist-info/RECORD
